_onigurumacffi.pypy311-pp73-x86_64-linux-gnu.so
onigurumacffi.py
onigurumacffi.libs/libonig-dcc10673.so.5.5.0
onigurumacffi-1.5.0.dist-info/METADATA
onigurumacffi-1.5.0.dist-info/WHEEL
onigurumacffi-1.5.0.dist-info/top_level.txt
onigurumacffi-1.5.0.dist-info/RECORD
onigurumacffi-1.5.0.dist-info/licenses/LICENSE
