Metadata-Version: 2.1
Name: onigurumacffi
Version: 1.5.0
Summary: python cffi bindings for the oniguruma regex engine
Home-page: https://github.com/asottile/onigurumacffi
Author: Anthony Sottile
Author-email: asottile@umich.edu
License: MIT
Classifier: Programming Language :: Python :: 3
Classifier: Programming Language :: Python :: 3 :: Only
Classifier: Programming Language :: Python :: Implementation :: CPython
Classifier: Programming Language :: Python :: Implementation :: PyPy
Requires-Python: >=3.10
License-File: LICENSE
Requires-Dist: cffi>=1
